bbc/BBC-News-Wrapper.md
bbc/__init__.py
bbc/exceptions.py
bbc/languages.py
bbc/news.py
bbc_news-1.0.2.dist-info/LICENSE
bbc_news-1.0.2.dist-info/METADATA
bbc_news-1.0.2.dist-info/WHEEL
bbc_news-1.0.2.dist-info/top_level.txt
bbc_news-1.0.2.dist-info/RECORD
