Metadata-Version: 2.1
Name: bbc-news
Version: 1.0.2
Summary: A simple and yet easy-to-use API for BBC News
Home-page: https://github.com/Sayad-Uddin-Tahsin/BBC-News-API
Author: Sayad Uddin Tahsin
Author-email: tahsin.ict@outlook.com
License: MIT
Project-URL: Bug Tracker, https://github.com/Sayad-Uddin-Tahsin/bbc-news/issues
Project-URL: PyPI, https://pypi.org/project/bbc-news/
Keywords: bbc-news,bbc-global,bbc-api,bbc-news-api,bbc-api-wrapper,tahsin-project
Classifier: Development Status :: 5 - Production/Stable
Classifier: Intended Audience :: Developers
Classifier: License :: OSI Approved :: MIT License
Classifier: Operating System :: OS Independent
Classifier: Programming Language :: Python :: 3.7
Classifier: Programming Language :: Python :: 3.8
Classifier: Programming Language :: Python :: 3.9
Classifier: Programming Language :: Python :: 3.10
Classifier: Programming Language :: Python :: 3.11
Requires-Python: >=3.7
License-File: LICENSE
Requires-Dist: requests >=2.28.2
